<DESIGN><genes string='8869506052020618657245041346477'/><foreground><fg_color n='0' blue='255' green='255' red='255'/><fg_color n='1' blue='79' green='229' red='255'/><fg_color n='2' blue='0' green='4' red='5'/><fg_color n='3' blue='12' green='219' red='255'/><fg_color n='4' blue='238' green='0' red='172'/><fg_color n='5' blue='223' green='72' red='25'/><fg_color n='6' blue='203' green='185' red='2'/><fg_color n='7' blue='0' green='0' red='0'/></foreground><background><bg_color n='0' blue='0' green='0' red='0'/><bg_color n='1' blue='255' green='255' red='255'/><bg_color n='2' blue='255' green='255' red='255'/><bg_color n='3' blue='255' green='255' red='255'/><bg_color n='4' blue='255' green='255' red='255'/><bg_color n='5' blue='255' green='255' red='255'/><bg_color n='6' blue='255' green='255' red='255'/><bg_color n='7' blue='255' green='255' red='255'/></background><fonts><font font='Onyx' type='secondary'/><font font='Onyx' type='secondary'/></fonts></DESIGN>
